geoquest/__about__.py
geoquest/__init__.py
geoquest/__version__.py
geoquest/county_info.py
geoquest/utils/ConvertSeconds.py
geoquest/utils/__init__.py
geoquest/utils/create_directory.py
geoquest-0.0.1.dist-info/METADATA
geoquest-0.0.1.dist-info/WHEEL
geoquest-0.0.1.dist-info/licenses/LICENSE
geoquest-0.0.1.dist-info/RECORD
