Metadata-Version: 2.3
Name: geoquest
Version: 0.0.1
Summary: Search, geocode, and reverse-geocode locations with ease using GeoQuest. A simple and intuitive API for location-based services.
Project-URL: Documentation, https://github.com/MohitShrestha/geoquest#readme
Project-URL: Issues, https://github.com/MohitShrestha/geoquest/issues
Project-URL: Source, https://github.com/MohitShrestha/geoquest
Author-email: Mohit Shrestha <contact@mohitshrestha.com.np>
License-Expression: MIT
License-File: LICENSE
Classifier: Development Status :: 4 - Beta
Classifier: Programming Language :: Python
Classifier: Programming Language :: Python :: 3.8
Classifier: Programming Language :: Python :: 3.9
Classifier: Programming Language :: Python :: 3.10
Classifier: Programming Language :: Python :: 3.11
Classifier: Programming Language :: Python :: 3.12
Classifier: Programming Language :: Python :: Implementation :: CPython
Classifier: Programming Language :: Python :: Implementation :: PyPy
Requires-Python: >=3.8
